Metadata-Version: 1.0
Name: suikanester
Version: 1.0.4
Summary: pypi upload test
Home-page: https://github.com/z2058550226/LearnPython
Author: suikajy
Author-email: 2058550226@qq.com
License: UNKNOWN
Keywords: tool
Platform: UNKNOWN
